hyperdock_langchain/__init__.py
hyperdock_langchain/connector.py
hyperdock_langchain/converter.py
hyperdock_langchain/dictionary.py
hyperdock_langchain-0.5.7.dist-info/METADATA
hyperdock_langchain-0.5.7.dist-info/WHEEL
hyperdock_langchain-0.5.7.dist-info/top_level.txt
hyperdock_langchain-0.5.7.dist-info/RECORD
