Metadata-Version: 2.4
Name: hyperdock-langchain
Version: 0.5.7
Summary: hyperdock-langchain
Author-email: Hyperpocket Team <hyperpocket@vessl.ai>
Requires-Python: >=3.10
Requires-Dist: langchain>=0.3.15
Requires-Dist: multiprocess>=0.70.17
